bppynndescent
