Metadata-Version: 1.2
Name: bppynndescent
Version: 0.1.0
Summary: Nearest Neighbor Descent
Home-page: http://github.com/lmcinnes/pynndescent
Author: Leland McInnes
Author-email: leland.mcinnes@gmail.com
Maintainer: Leland McInnes
Maintainer-email: leland.mcinnes@gmail.com
License: BSD
Keywords: nearest neighbor,knn,ANN
Platform: UNKNOWN
Classifier: Development Status :: 3 - Alpha
Classifier: Intended Audience :: Science/Research
Classifier: Intended Audience :: Developers
Classifier: License :: OSI Approved
Classifier: Programming Language :: C
Classifier: Programming Language :: Python
Classifier: Topic :: Software Development
Classifier: Topic :: Scientific/Engineering
Classifier: Operating System :: Microsoft :: Windows
Classifier: Operating System :: POSIX
Classifier: Operating System :: Unix
Classifier: Operating System :: MacOS
Classifier: Programming Language :: Python :: 3.6
Classifier: Programming Language :: Python :: 3.7
Classifier: Programming Language :: Python :: 3.8
